asynqp/__init__.py
asynqp/_exceptions.py
asynqp/amqp0-9-1.xml
asynqp/amqptypes.py
asynqp/channel.py
asynqp/connection.py
asynqp/exceptions.py
asynqp/exchange.py
asynqp/frames.py
asynqp/log.py
asynqp/message.py
asynqp/protocol.py
asynqp/queue.py
asynqp/routing.py
asynqp/serialisation.py
asynqp/spec.py
asynqp-0.6.dist-info/LICENSE
asynqp-0.6.dist-info/METADATA
asynqp-0.6.dist-info/WHEEL
asynqp-0.6.dist-info/top_level.txt
asynqp-0.6.dist-info/RECORD
